runner.py
rmt/__init__.py
rmt/__main__.py
rmt/kinematics.py
rmt/rmt.py
robmodel/__init__.py
robmodel/connectivity.py
robmodel/frames.py
robmodel/geometry.py
robmodel/inertia.py
robmodel/jposes.py
robmodel/ordering.py
robmodel/treeutils.py
robmodel/convert/__init__.py
robmodel/convert/utils.py
robmodel/convert/kindsl/__init__.py
robmodel/convert/kindsl/exp.py
robmodel/convert/kindsl/imp.py
robmodel/convert/kindsl/kindsl.tx
robmodel/convert/urdf/__init__.py
robmodel/convert/urdf/exp.py
robmodel/convert/urdf/imp.py
robmodel/convert/yaml/__init__.py
robmodel/convert/yaml/exp.py
robmodel/convert/yaml/imp.py
robot_model_tools-0.1.0.dist-info/LICENSE
robot_model_tools-0.1.0.dist-info/METADATA
robot_model_tools-0.1.0.dist-info/WHEEL
robot_model_tools-0.1.0.dist-info/entry_points.txt
robot_model_tools-0.1.0.dist-info/top_level.txt
robot_model_tools-0.1.0.dist-info/RECORD
