Metadata-Version: 2.1
Name: robot-model-tools
Version: 0.1.0
Summary: Misc utilities to work with robot model formats
Author-email: Marco Frigerio <marco.frigerio17@pm.me>
License: Copyright (c) 2019-2020, Marco Frigerio
Project-URL: home, https://github.com/mfrigerio17/robot-model-tools
Requires-Python: >=3.4
License-File: LICENSE
Requires-Dist: kgprim
Requires-Dist: networkx
Requires-Dist: numpy
Requires-Dist: pyyaml
Requires-Dist: pygraphviz
Requires-Dist: textX
Requires-Dist: mako
